vat_id_validator/__init__.py
vat_id_validator/client.py
vat_id_validator/py.typed
vat_id_validator/types.py
vat_id_validator-1.0.0.dist-info/METADATA
vat_id_validator-1.0.0.dist-info/WHEEL
vat_id_validator-1.0.0.dist-info/RECORD
