Metadata-Version: 2.4
Name: vat-id-validator
Version: 1.0.0
Summary: Python client for VAT ID Validator API - Validate EU VAT numbers using VIES
Project-URL: Homepage, https://github.com/robrace82/VAT-ID-Validator-API
Project-URL: Repository, https://github.com/robrace82/VAT-ID-Validator-API
Project-URL: Issues, https://github.com/robrace82/VAT-ID-Validator-API/issues
Author: API Magik Team
License: MIT
Keywords: eu,rapidapi,tax,validation,vat,vat-number,vat-validator,vies
Classifier: Development Status :: 5 - Production/Stable
Classifier: Intended Audience :: Developers
Classifier: License :: OSI Approved :: MIT License
Classifier: Programming Language :: Python :: 3
Classifier: Programming Language :: Python :: 3.8
Classifier: Programming Language :: Python :: 3.9
Classifier: Programming Language :: Python :: 3.10
Classifier: Programming Language :: Python :: 3.11
Classifier: Programming Language :: Python :: 3.12
Classifier: Topic :: Software Development :: Libraries :: Python Modules
Classifier: Typing :: Typed
Requires-Python: >=3.8
Requires-Dist: requests>=2.31.0
Provides-Extra: dev
Requires-Dist: black>=23.0.0; extra == 'dev'
Requires-Dist: mypy>=1.0.0; extra == 'dev'
Requires-Dist: pytest>=7.0.0; extra == 'dev'
Requires-Dist: types-requests>=2.31.0; extra == 'dev'
